{
  "namespace": "_staging_backport",
  "short_name": "dataset_4900_same_sex_married_households_in_the_us_values",
  "name": "Same-sex married households in the US",
  "description": "",
  "source_name": "Our World in Data",
  "url": "https://owid.cloud/admin/datasets/4900",
  "file_extension": "feather",
  "date_accessed": "2022-04-08T13:50:43.585808",
  "is_public": true,
  "publication_date": "latest",
  "owid_data_url": "https://walden.nyc3.digitaloceanspaces.com/_staging_backport/latest/dataset_4900_same_sex_married_households_in_the_us_values.feather",
  "md5": "71cc3d6b0639eeeb2ca072fa79548ef8"
}
