{
  "namespace": "_staging_backport",
  "short_name": "dataset_1861_earnings_and_labour_cost_values",
  "name": "Earnings and labour cost",
  "description": "This is a dataset imported by the automated fetcher",
  "source_name": "Our World in Data",
  "url": "https://owid.cloud/admin/datasets/1861",
  "file_extension": "feather",
  "date_accessed": "2022-04-14T13:06:52.502312",
  "is_public": true,
  "publication_date": "latest",
  "owid_data_url": "https://walden.nyc3.digitaloceanspaces.com/_staging_backport/latest/dataset_1861_earnings_and_labour_cost_values.feather",
  "md5": "f89d8028df819804c87ebe847826c4e5"
}
