{
  "namespace": "backport",
  "short_name": "dataset_5374_climate_change_impacts_values",
  "name": "Climate change impacts",
  "description": "Code: https://github.com/owid/importers/tree/master/climate_change\n(run `python3 src/main.py` to update all sources)\n\nOutput files: https://github.com/owid/importers/tree/master/climate_change/output",
  "source_name": "Our World in Data catalog backport",
  "url": "https://owid.cloud/admin/datasets/5374",
  "file_extension": "feather",
  "date_accessed": "2022-05-27T08:19:44.116341",
  "is_public": true,
  "version": "latest",
  "publication_date": "latest",
  "owid_data_url": "https://walden.nyc3.digitaloceanspaces.com/backport/latest/dataset_5374_climate_change_impacts_values.feather",
  "md5": "a8a99d18c055f842b6ee691665a519d2"
}
