{
  "namespace": "backport",
  "short_name": "dataset_5141_te_17_13_union_config",
  "name": "Grapher metadata for dataset_5141_te_17_13_union",
  "description": "core-econ.org",
  "source_name": "Our World in Data catalog backport",
  "url": "https://owid.cloud/admin/datasets/5141",
  "file_extension": "json",
  "date_accessed": "2022-09-01T07:25:45.825105",
  "is_public": false,
  "version": "latest",
  "publication_date": "latest",
  "origin_md5": "2d009a6c5b302c392d308f9315f5e58b",
  "owid_data_url": "https://walden.nyc3.digitaloceanspaces.com/backport/latest/dataset_5141_te_17_13_union_config.json",
  "md5": "27efdd9f362b6f254235ae0d783ac3ca"
}
