{
  "namespace": "backport",
  "short_name": "dataset_3172_te_19_5_config",
  "name": "Grapher metadata for dataset_3172_te_19_5",
  "description": "core-econ.org",
  "source_name": "Our World in Data catalog backport",
  "url": "https://owid.cloud/admin/datasets/3172",
  "file_extension": "json",
  "date_accessed": "2022-06-10T08:54:12.165007",
  "is_public": false,
  "version": "latest",
  "publication_date": "latest",
  "origin_md5": "8487f703a528815832b70611c2b9963a",
  "owid_data_url": "https://walden.nyc3.digitaloceanspaces.com/backport/latest/dataset_3172_te_19_5_config.json",
  "md5": "11e9275e647cbbde4684f9a5a003b6b0"
}
