{
  "namespace": "backport",
  "short_name": "dataset_5114_te_19_30b_2_values",
  "name": "TE-19.30b_2",
  "description": "core-econ.org",
  "source_name": "Our World in Data catalog backport",
  "url": "https://owid.cloud/admin/datasets/5114",
  "file_extension": "feather",
  "date_accessed": "2022-06-09T07:38:21.422168",
  "is_public": false,
  "version": "latest",
  "publication_date": "latest",
  "owid_data_url": "https://walden.nyc3.digitaloceanspaces.com/backport/latest/dataset_5114_te_19_30b_2_values.feather",
  "md5": "35886ad78e273c1fc59d9c2bfa61fc51"
}
