{
  "namespace": "backport",
  "short_name": "dataset_5151_figure_19_3_updated_config",
  "name": "Grapher metadata for dataset_5151_figure_19_3_updated",
  "description": "core-econ.org",
  "source_name": "Our World in Data catalog backport",
  "url": "https://owid.cloud/admin/datasets/5151",
  "file_extension": "json",
  "date_accessed": "2022-09-01T07:57:23.775144",
  "is_public": false,
  "version": "latest",
  "publication_date": "latest",
  "origin_md5": "4d53b3a1d66e2a2da854d6acedcd4666",
  "owid_data_url": "https://walden.nyc3.digitaloceanspaces.com/backport/latest/dataset_5151_figure_19_3_updated_config.json",
  "md5": "1201a39bc342b76d54657719f63090e9"
}
