{
  "namespace": "backport",
  "short_name": "dataset_2483_five_year_cancer_survival_rates__allemani_et_al_values",
  "name": "Five year cancer survival rates - Allemani et al. ",
  "description": "",
  "source_name": "Our World in Data catalog backport",
  "url": "https://owid.cloud/admin/datasets/2483",
  "file_extension": "feather",
  "date_accessed": "2022-09-01T07:27:44.376005",
  "is_public": true,
  "version": "latest",
  "publication_date": "latest",
  "owid_data_url": "https://walden.nyc3.digitaloceanspaces.com/backport/latest/dataset_2483_five_year_cancer_survival_rates__allemani_et_al_values.feather",
  "md5": "0ada74cafab5d87fd3b7d1cef6d82850"
}
