{
  "namespace": "backport",
  "short_name": "dataset_5105_figure_17_1c_1_config",
  "name": "Grapher metadata for dataset_5105_figure_17_1c_1",
  "description": "core-econ.org",
  "source_name": "Our World in Data catalog backport",
  "url": "https://owid.cloud/admin/datasets/5105",
  "file_extension": "json",
  "date_accessed": "2022-09-01T16:12:36.180620",
  "is_public": false,
  "version": "latest",
  "publication_date": "latest",
  "origin_md5": "66f81ab423d706a6fd1adf44bb9a4bd7",
  "owid_data_url": "https://walden.nyc3.digitaloceanspaces.com/backport/latest/dataset_5105_figure_17_1c_1_config.json",
  "md5": "04fb49dc5c80f6029bd25d69c89203ad"
}
