{
  "namespace": "backport",
  "short_name": "dataset_5102_figure_17_1a_2_config",
  "name": "Grapher metadata for dataset_5102_figure_17_1a_2",
  "description": "core-econ.org",
  "source_name": "Our World in Data catalog backport",
  "url": "https://owid.cloud/admin/datasets/5102",
  "file_extension": "json",
  "date_accessed": "2022-06-09T07:28:44.786184",
  "is_public": false,
  "version": "latest",
  "publication_date": "latest",
  "origin_md5": "cfe2e181591734a544d9828751d46fa7",
  "owid_data_url": "https://walden.nyc3.digitaloceanspaces.com/backport/latest/dataset_5102_figure_17_1a_2_config.json",
  "md5": "b015d55475c4434a5b53fcebefc6ce0d"
}
