{
  "namespace": "backport",
  "short_name": "dataset_5800_national_poverty_lines__jolliffe_et_al__2022_values",
  "name": "National poverty lines (Jolliffe et al., 2022)",
  "description": "",
  "source_name": "Our World in Data catalog backport",
  "url": "https://owid.cloud/admin/datasets/5800",
  "file_extension": "feather",
  "date_accessed": "2022-10-11T14:45:02.926739",
  "is_public": true,
  "version": "latest",
  "publication_date": "latest",
  "owid_data_url": "https://walden.nyc3.digitaloceanspaces.com/backport/latest/dataset_5800_national_poverty_lines__jolliffe_et_al__2022_values.feather",
  "md5": "798049e3c0011df56b546a2f793a45f1"
}
