{
  "namespace": "backport",
  "short_name": "dataset_5633_democracy__polity_5_values",
  "name": "Democracy - Polity 5",
  "description": "",
  "source_name": "Our World in Data catalog backport",
  "url": "https://owid.cloud/admin/datasets/5633",
  "file_extension": "feather",
  "date_accessed": "2022-06-21T18:02:27.423970",
  "is_public": true,
  "version": "latest",
  "publication_date": "latest",
  "owid_data_url": "https://walden.nyc3.digitaloceanspaces.com/backport/latest/dataset_5633_democracy__polity_5_values.feather",
  "md5": "15341fa1abadf2e45ef4b63d4e5cf06d"
}
