{
  "namespace": "backport",
  "short_name": "dataset_5669_un_sdg__2022_07_07_values",
  "name": "un_sdg__2022_07_07",
  "description": "The United Nations Sustainable Development Goal (SDG) dataset is the primary collection of data tracking progress towards the SDG indicators, compiled from officially-recognized international sources.",
  "source_name": "Our World in Data catalog backport",
  "url": "https://owid.cloud/admin/datasets/5669",
  "file_extension": "feather",
  "date_accessed": "2022-11-02T20:16:05.226160",
  "is_public": true,
  "version": "latest",
  "publication_date": "latest",
  "owid_data_url": "https://walden.nyc3.digitaloceanspaces.com/backport/latest/dataset_5669_un_sdg__2022_07_07_values.feather",
  "md5": "0b6c9f14033330c41d86b5d17af5760d"
}
