{
  "namespace": "backport",
  "short_name": "dataset_2958_precipitation_anomaly_in_us__noaa_config",
  "name": "Grapher metadata for dataset_2958_precipitation_anomaly_in_us__noaa",
  "description": "",
  "source_name": "Our World in Data catalog backport",
  "url": "https://owid.cloud/admin/datasets/2958",
  "file_extension": "json",
  "date_accessed": "2022-09-07T15:39:46.830184",
  "is_public": true,
  "version": "latest",
  "publication_date": "latest",
  "origin_md5": "e6d029aba515de22998ce88ee9c3ebb2",
  "md5": "4f5449019b9f4b6c5e11264e0ca54931"
}
